test.py
test_api.py
pvblocks/__init__.py
pvblocks/__main__.py
pvblocks/constants.py
pvblocks/exceptions.py
pvblocks/pvblocks_api.py
pvblocks/pvblocks_system.py
pvblocks-0.1.7.dist-info/licenses/LICENSE
pvblocks-0.1.7.dist-info/METADATA
pvblocks-0.1.7.dist-info/WHEEL
pvblocks-0.1.7.dist-info/top_level.txt
pvblocks-0.1.7.dist-info/RECORD
